{
    "Status_In_MainMenu": {
        "desc": "处于主界面",
        "recognition": "And",
        "all_of": [
            "UI_MainMenu_combatants",
            "UI_MainMenu_team",
            "UI_MainMenu_vehicle",
            "UI_MainMenu_base"
        ]
    },
    "Status_Loading_Screen": {
        "desc": "处于加载界面",
        "recognition": {
            "type": "TemplateMatch",
            "param": {
                "template": "UI/Loading/1.png",
                "green_mask": true
            }
        }
    },
    "Status_In_Combat": {
        "desc": "处于出击界面",
        "recognition": "And",
        "all_of": [
            "UI_Combat_MainStory",
            "UI_Combat_MaterialQuests",
            "UI_Combat_SkillMaterial"
        ]
    },
    "Status_In_Stage": {
        "desc": "处于战斗中",
        "recognition": "And",
        "all_of": [
            "UI_Combat_InStage_active"
        ]
    }
}
